pyprimos/__init__.py
pyprimos-1.0.dist-info/LICENSE
pyprimos-1.0.dist-info/METADATA
pyprimos-1.0.dist-info/WHEEL
pyprimos-1.0.dist-info/top_level.txt
pyprimos-1.0.dist-info/RECORD
