Metadata-Version: 2.1
Name: pyprimos
Version: 1.0
Summary: Es una herramienta para calcular los primos entre 1 y n.
Home-page: UNKNOWN
Author: Leonardo Arias
Author-email: neoleoal@gmail.com
License: GNU GPLv3
Keywords: pyprimos mathematical operations primos
Platform: UNKNOWN
Classifier: Development Status :: 4 - Beta
Classifier: Intended Audience :: Developers
Classifier: Topic :: Utilities
Classifier: License :: OSI Approved :: GNU General Public License v3 (GPLv3)
Classifier: Programming Language :: Python :: 3
Classifier: Operating System :: OS Independent
